pavimentados/__init__.py
pavimentados/analyzers/__init__.py
pavimentados/analyzers/calculators.py
pavimentados/analyzers/exceptions.py
pavimentados/analyzers/gps_sources.py
pavimentados/analyzers/utils.py
pavimentados/configs/__init__.py
pavimentados/configs/models_general.json
pavimentados/configs/utils.py
pavimentados/configs/workflows_general.json
pavimentados/models/__init__.py
pavimentados/models/base.py
pavimentados/models/siamese.py
pavimentados/models/yolov8.py
pavimentados/processing/__init__.py
pavimentados/processing/exceptions.py
pavimentados/processing/processors.py
pavimentados/processing/sources.py
pavimentados/processing/utils.py
pavimentados/processing/workflows.py
pavimentados-1.0.5.dist-info/LICENSE.md
pavimentados-1.0.5.dist-info/METADATA
pavimentados-1.0.5.dist-info/WHEEL
pavimentados-1.0.5.dist-info/top_level.txt
pavimentados-1.0.5.dist-info/RECORD
