Metadata-Version: 2.1
Name: pavimentados
Version: 1.0.5
Summary: A python package Library which implement IA algorithms to detect cracks and failures on roads. The package is wrapper around all the models and provides an interfaces to use them properly
Author: Jose Maria Marquez Blanco
Author-email: jose.marquez.blanco@gmail.com
Keywords: Machine Learning,crack detections,computer vision,safe road
Classifier: Development Status :: 3 - Alpha
Classifier: Programming Language :: Python :: 3
Classifier: Operating System :: OS Independent
Classifier: Programming Language :: Python :: 3.9
Classifier: Operating System :: OS Independent
Classifier: Programming Language :: Python :: 3.10
Classifier: Operating System :: OS Independent
Classifier: Programming Language :: Python :: 3.11
Requires-Python: >=3.9
License-File: LICENSE.md
Requires-Dist: pandas >=1.0.3
Requires-Dist: numpy <2.0.0
Requires-Dist: pynmea2 >=1.15.0
Requires-Dist: tqdm
Requires-Dist: Pillow ==9.3.0
Requires-Dist: opencv-python >=4.3.0.34
Requires-Dist: scipy >=1.4.1
Requires-Dist: onnxruntime >=1.18.0
Requires-Dist: onnxruntime-gpu >=1.18.0
Requires-Dist: ultralytics ~=8.2.0
Requires-Dist: xmltodict
